setup.py
src/radar/__init__.py
src/radar/defaults.py
src/radar/exceptions.py
src/radar/helpers.py
src/radar/test.py
src/radar/utils.py
src/radar.egg-info/PKG-INFO
src/radar.egg-info/SOURCES.txt
src/radar.egg-info/dependency_links.txt
src/radar.egg-info/top_level.txt